flexivit_pytorch/__init__.py
flexivit_pytorch/flexivit.py
flexivit_pytorch/patch_embed.py
flexivit_pytorch/utils.py
flexivit_pytorch-0.0.1.dist-info/LICENSE
flexivit_pytorch-0.0.1.dist-info/METADATA
flexivit_pytorch-0.0.1.dist-info/WHEEL
flexivit_pytorch-0.0.1.dist-info/top_level.txt
flexivit_pytorch-0.0.1.dist-info/RECORD
