Metadata-Version: 2.1
Name: flexivit-pytorch
Version: 0.0.1
Summary: FlexiViT: Vision Transformer with Flexible Patch Size
Home-page: https://github.com/bwconrad/flexivit
Author: Ben Conrad
Author-email: benwconrad@gmail.com
License: MIT
Keywords: transformers,artificial intelligence,computer vision,deep learning
Classifier: Intended Audience :: Developers
Classifier: Topic :: Scientific/Engineering :: Artificial Intelligence
Classifier: License :: OSI Approved :: MIT License
Requires-Python: >=3.8
License-File: LICENSE
Requires-Dist: einops (>=0.6.0)
Requires-Dist: functorch (>=1.13.1)
Requires-Dist: numpy (>=1.24.2)
Requires-Dist: timm (>=0.8.15.dev0)
Requires-Dist: torch (>=1.13.1)
